README.rst
setup.py
pyparty/__init__.py
pyparty/config.py
pyparty/multi.py
pyparty/noise.py
pyparty/plots.py
pyparty/scale.py
pyparty/utils.py
pyparty.egg-info/PKG-INFO
pyparty.egg-info/SOURCES.txt
pyparty.egg-info/dependency_links.txt
pyparty.egg-info/entry_points.txt
pyparty.egg-info/top_level.txt
pyparty/background/__init__.py
pyparty/background/bg_utils.py
pyparty/bundled/__init__.py
pyparty/bundled/gwu.css
pyparty/bundled/louic.css
pyparty/bundled/nbstyles.py
pyparty/bundled/purisa.css
pyparty/bundled/slender.css
pyparty/bundled/test.css
pyparty/data/__init__.py
pyparty/data/coverimage.png
pyparty/data/gwu.png
pyparty/data/lena_who.jpg
pyparty/data/nanobinary.tif
pyparty/data/nanogold.tif
pyparty/data/nanolabels.tif
pyparty/data/test_binary.png
pyparty/data/test_labeled.png
pyparty/data/test_noise.png
pyparty/data/test_raster.png
pyparty/descriptors/__init__.py
pyparty/descriptors/api.py
pyparty/descriptors/user_descriptors.py
pyparty/logging_utils/__init__.py
pyparty/logging_utils/logger.py
pyparty/patterns/__init__.py
pyparty/patterns/elements.py
pyparty/scripts/__init__.py
pyparty/scripts/objectmodeling/BSA.py
pyparty/scripts/objectmodeling/__init__.py
pyparty/scripts/objectmodeling/_configobjhunt.py
pyparty/scripts/objectmodeling/descriptor_model.py
pyparty/scripts/objectmodeling/fitutils.py
pyparty/scripts/objectmodeling/objecthunt.py
pyparty/shape_models/__init__.py
pyparty/shape_models/abstract_shape.py
pyparty/shape_models/api.py
pyparty/shape_models/basic.py
pyparty/shape_models/io.py
pyparty/shape_models/multi.py
pyparty/shape_models/polygons.py
pyparty/tools/__init__.py
pyparty/tools/arraytools.py
pyparty/tools/canvas.py
pyparty/tools/grids.py
pyparty/tools/manager.py
pyparty/tools/thresholding.py
pyparty/trait_types/__init__.py
pyparty/trait_types/intornone.py
pyparty/trait_types/listorparticle.py
pyparty/trait_types/metaparticle.py