Metadata-Version: 1.1
Name: pyparty
Version: 0.3.0
Summary: Tools for patterning 2d-shapes on ndarrays
Home-page: http://pypi.python.org/pypi/pyparty/
Author: Adam Hughes
Author-email: hughesadam87@gmail.com
License: LICENSE.txt
Download-URL: https://github.com/hugadams/pyparty
Platform: UNKNOWN
Classifier: Development Status :: 2 - Pre-Alpha
Classifier: Environment :: Console
Classifier: Intended Audience :: Science/Research
Classifier: Intended Audience :: Developers
Classifier: Natural Language :: English
Classifier: Operating System :: Microsoft :: Windows
Classifier: Operating System :: POSIX
Classifier: Operating System :: Unix
Classifier: Operating System :: MacOS
Classifier: Programming Language :: Python :: 2
Classifier: Topic :: Scientific/Engineering :: Visualization
Classifier: Topic :: Scientific/Engineering :: Physics
